[
    {
        "domain": ".shadowverse-portal.com",
        "expirationDate": 1759233699,
        "hostOnly": false,
        "httpOnly": false,
        "name": "__ulfpc",
        "path": "/",
        "sameSite": "unspecified",
        "secure": false,
        "session": false,
        "storeId": "0",
        "value": "202408262101391994",
        "id": 1
    },
    {
        "domain": ".shadowverse-portal.com",
        "expirationDate": 1759233699,
        "hostOnly": false,
        "httpOnly": false,
        "name": "__utma",
        "path": "/",
        "sameSite": "unspecified",
        "secure": false,
        "session": false,
        "storeId": "0",
        "value": "14403701.335493095.1724673700.1724673700.1724673700.1",
        "id": 2
    },
    {
        "domain": ".shadowverse-portal.com",
        "expirationDate": 1724675499,
        "hostOnly": false,
        "httpOnly": false,
        "name": "__utmb",
        "path": "/",
        "sameSite": "unspecified",
        "secure": false,
        "session": false,
        "storeId": "0",
        "value": "14403701.1.10.1724673700",
        "id": 3
    },
    {
        "domain": ".shadowverse-portal.com",
        "hostOnly": false,
        "httpOnly": false,
        "name": "__utmc",
        "path": "/",
        "sameSite": "unspecified",
        "secure": false,
        "session": true,
        "storeId": "0",
        "value": "14403701",
        "id": 4
    },
    {
        "domain": ".shadowverse-portal.com",
        "expirationDate": 1740441699,
        "hostOnly": false,
        "httpOnly": false,
        "name": "__utmz",
        "path": "/",
        "sameSite": "unspecified",
        "secure": false,
        "session": false,
        "storeId": "0",
        "value": "14403701.1724673700.1.1.utmcsr=(direct)|utmccn=(direct)|utmcmd=(none)",
        "id": 5
    },
    {
        "domain": ".shadowverse-portal.com",
        "expirationDate": 1759233700,
        "hostOnly": false,
        "httpOnly": false,
        "name": "_ga",
        "path": "/",
        "sameSite": "unspecified",
        "secure": false,
        "session": false,
        "storeId": "0",
        "value": "GA1.1.173462239.1724673700",
        "id": 6
    },
    {
        "domain": ".shadowverse-portal.com",
        "expirationDate": 1759233700,
        "hostOnly": false,
        "httpOnly": false,
        "name": "_ga_TYR90Q6TXM",
        "path": "/",
        "sameSite": "unspecified",
        "secure": false,
        "session": false,
        "storeId": "0",
        "value": "GS1.1.1724673700.1.0.1724673700.0.0.0",
        "id": 7
    },
    {
        "domain": ".shadowverse-portal.com",
        "expirationDate": 1756209699,
        "hostOnly": false,
        "httpOnly": false,
        "name": "OptanonAlertBoxClosed",
        "path": "/",
        "sameSite": "lax",
        "secure": false,
        "session": false,
        "storeId": "0",
        "value": "2024-08-26T12:01:39.738Z",
        "id": 8
    },
    {
        "domain": ".shadowverse-portal.com",
        "expirationDate": 1756209699,
        "hostOnly": false,
        "httpOnly": false,
        "name": "OptanonConsent",
        "path": "/",
        "sameSite": "lax",
        "secure": false,
        "session": false,
        "storeId": "0",
        "value": "isGpcEnabled=0&datestamp=Mon+Aug+26+2024+21%3A01%3A39+GMT%2B0900+(%E6%97%A5%E6%9C%AC%E6%A8%99%E6%BA%96%E6%99%82)&version=202306.1.0&browserGpcFlag=0&isIABGlobal=false&hosts=&consentId=8094a6c6-f2c1-42b8-b823-07a13241380f&interactionCount=2&landingPath=NotLandingPage&groups=C0001%3A1%2CC0002%3A1&AwaitingReconsent=false",
        "id": 9
    },
    {
        "domain": "shadowverse-portal.com",
        "expirationDate": 1724684476,
        "hostOnly": true,
        "httpOnly": true,
        "name": "sid",
        "path": "/",
        "sameSite": "unspecified",
        "secure": true,
        "session": false,
        "storeId": "0",
        "value": "1bdb9d806c8152a3d962d5fa0ef527fbfc931b12b5a27ab7ce2dea80b78b0582",
        "id": 10
    }
]